spinopt/__init__.py
spinopt/interface.py
spinopt-24.7.2.dist-info/licenses/LICENSE
spinopt-24.7.2.dist-info/WHEEL
spinopt-24.7.2.dist-info/METADATA
spinopt-24.7.2.dist-info/RECORD
