Metadata-Version: 2.4
Name: spinopt
Version: 24.7.2
Summary: Scipy interface to NLOPT
Keywords: Optimization
Author: Martin van der Schans
License-File: LICENSE
Requires-Dist: numpy
Requires-Dist: nlopt
Requires-Dist: pytest ; extra == "dev"
Requires-Dist: ruff ; extra == "dev"
Project-URL: repository, https://github.com/mvds314/spinopt
Provides-Extra: dev
